trn/__init__.py
trn-0.1.10.dist-info/METADATA
trn-0.1.10.dist-info/WHEEL
trn-0.1.10.dist-info/entry_points.txt
trn-0.1.10.dist-info/top_level.txt
trn-0.1.10.dist-info/RECORD
