Metadata-Version: 2.4
Name: trn
Version: 0.1.10
Summary: CLI tool to translate text with LLMs
Author-email: Alexander Ryabov <alex.ryabov@gmail.com>
Project-URL: Homepage, https://github.com/haron/trn
Project-URL: Issues, https://github.com/haron/trn/issues
Classifier: Programming Language :: Python :: 3
Classifier: Operating System :: OS Independent
Requires-Python: >=3.12
Requires-Dist: configargparse>=1.7.1
Requires-Dist: curl-cffi>=0.13.0
Requires-Dist: html2text>=2025.4.15
Requires-Dist: llm>=0.27.1
Requires-Dist: llm-anthropic>=0.18
Requires-Dist: llm-gemini>=0.25
Requires-Dist: pyperclip>=1.9.0
